[
  {
    "title": "The Weeknd - Starboy ft. Daft Punk (Official Video)",
    "url": "https://kworb.net/youtube../video/34Na4j8AVgA.html",
    "views": "2,401,154,692",
    "yesterday": "695,624",
    "publish": "2016/09"
  },
  {
    "title": "The Weeknd - The Hills",
    "url": "https://kworb.net/youtube../video/yzTuBuRdAyA.html",
    "views": "2,086,693,824",
    "yesterday": "547,657",
    "publish": "2015/05"
  },
  {
    "title": "The Weeknd - Save Your Tears (Official Music Video)",
    "url": "https://kworb.net/youtube../video/XXYlFuWEuKI.html",
    "views": "1,503,106,673",
    "yesterday": "919,313",
    "publish": "2021/01"
  },
  {
    "title": "The Weeknd - Can't Feel My Face (Official Video)",
    "url": "https://kworb.net/youtube../video/KEI4qSrkPAs.html",
    "views": "1,392,623,573",
    "yesterday": "288,156",
    "publish": "2015/07"
  },
  {
    "title": "The Weeknd - I Feel It Coming ft. Daft Punk (Official Video)",
    "url": "https://kworb.net/youtube../video/qFLhGq0060w.html",
    "views": "1,188,570,910",
    "yesterday": "328,484",
    "publish": "2017/03"
  },
  {
    "title": "The Weeknd - Call Out My Name (Official Video)",
    "url": "https://kworb.net/youtube../video/M4ZoCHID9GI.html",
    "views": "950,043,747",
    "yesterday": "424,921",
    "publish": "2018/04"
  },
  {
    "title": "Future - Low Life (Official Music Video) ft. The Weeknd",
    "url": "https://kworb.net/youtube../video/K_9tX4eHztY.html",
    "views": "824,103,313",
    "yesterday": "178,520",
    "publish": "2016/03"
  },
  {
    "title": "Ariana Grande, The Weeknd - Love Me Harder",
    "url": "https://kworb.net/youtube../video/g5qU7p7yOY8.html",
    "views": "819,590,345",
    "yesterday": "103,863",
    "publish": "2014/11"
  },
  {
    "title": "The Weeknd - Blinding Lights (Official Video)",
    "url": "https://kworb.net/youtube../video/4NRXx6U8ABQ.html",
    "views": "807,634,246",
    "yesterday": "458,370",
    "publish": "2020/01"
  },
  {
    "title": "The Weeknd - Blinding Lights (Official Audio)",
    "url": "https://kworb.net/youtube../video/fHI8X4OXluQ.html",
    "views": "796,166,735",
    "yesterday": "226,298",
    "publish": "2019/11"
  },
  {
    "title": "The Weeknd - Earned It (Fifty Shades Of Grey)",
    "url": "https://kworb.net/youtube../video/waU75jdUnYw.html",
    "views": "769,357,160",
    "yesterday": "122,272",
    "publish": "2015/01"
  },
  {
    "title": "Ty Dolla $ign - Or Nah (feat. The Weeknd, Wiz Khalifa & DJ Mustard) [Official Music Video]",
    "url": "https://kworb.net/youtube../video/TUj0otkJEBo.html",
    "views": "725,986,677",
    "yesterday": "120,311",
    "publish": "2014/06"
  },
  {
    "title": "The Weeknd - Often (NSFW) (Official Video)",
    "url": "https://kworb.net/youtube../video/JPIhUaONiLU.html",
    "views": "527,496,563",
    "yesterday": "103,091",
    "publish": "2014/08"
  },
  {
    "title": "The Weeknd - Reminder (Official Video)",
    "url": "https://kworb.net/youtube../video/JZjAg6fK-BQ.html",
    "views": "510,296,832",
    "yesterday": "347,846",
    "publish": "2017/02"
  },
  {
    "title": "The Weeknd & Ariana Grande - Save Your Tears (Remix) (Official Video)",
    "url": "https://kworb.net/youtube../video/LIIDh-qI9oI.html",
    "views": "301,501,666",
    "yesterday": "160,957",
    "publish": "2021/04"
  },
  {
    "title": "The Weeknd - Earned It (from Fifty Shades Of Grey) (Official Lyric Video)",
    "url": "https://kworb.net/youtube../video/xe_iCkFsQKE.html",
    "views": "291,655,737",
    "yesterday": "115,957",
    "publish": "2015/01"
  },
  {
    "title": "Doja Cat, The Weeknd - You Right (Official Video)",
    "url": "https://kworb.net/youtube../video/JXgV1rXUoME.html",
    "views": "283,533,612",
    "yesterday": "191,931",
    "publish": "2021/06"
  },
  {
    "title": "The Weeknd, Kendrick Lamar - Pray For Me (Official Lyric Video)",
    "url": "https://kworb.net/youtube../video/XR7Ev14vUh8.html",
    "views": "262,390,495",
    "yesterday": "79,573",
    "publish": "2018/03"
  },
  {
    "title": "The Weeknd - Wicked Games (Official Video - Explicit)",
    "url": "https://kworb.net/youtube../video/O1OTWCd40bc.html",
    "views": "257,689,750",
    "yesterday": "65,336",
    "publish": "2012/10"
  },
  {
    "title": "ROSALÍA - LA FAMA (Official Video) ft. The Weeknd",
    "url": "https://kworb.net/youtube../video/e-CEd6xrRQc.html",
    "views": "255,249,131",
    "yesterday": "118,905",
    "publish": "2021/11"
  },
  {
    "title": "The Weeknd, Ariana Grande - Die For You (Remix / Lyric Video)",
    "url": "https://kworb.net/youtube../video/YQ-qToZUybM.html",
    "views": "242,357,878",
    "yesterday": "568,295",
    "publish": "2023/02"
  },
  {
    "title": "The Weeknd & Ariana Grande – Save Your Tears (Live on The 2021 iHeart Radio Music Awards)",
    "url": "https://kworb.net/youtube../video/s37x2VSZrLw.html",
    "views": "234,593,764",
    "yesterday": "268,986",
    "publish": "2021/06"
  },
  {
    "title": "The Weeknd - False Alarm (Official Video)",
    "url": "https://kworb.net/youtube../video/CW5oGRx9CLM.html",
    "views": "229,118,999",
    "yesterday": "60,331",
    "publish": "2016/10"
  },
  {
    "title": "Lana Del Rey - Lust For Life (Official Video) ft. The Weeknd",
    "url": "https://kworb.net/youtube../video/eP4eqhWc7sI.html",
    "views": "222,205,288",
    "yesterday": "52,739",
    "publish": "2017/05"
  },
  {
    "title": "Gesaffelstein & The Weeknd - Lost in the Fire (Official Video)",
    "url": "https://kworb.net/youtube../video/ZGDGdRIxvd0.html",
    "views": "220,329,253",
    "yesterday": "113,787",
    "publish": "2019/01"
  },
  {
    "title": "The Weeknd - Starboy (Live From The Victoria’s Secret Fashion Show 2016 in Paris)",
    "url": "https://kworb.net/youtube../video/vuT_bXzhqhY.html",
    "views": "215,849,038",
    "yesterday": "67,285",
    "publish": "2016/12"
  },
  {
    "title": "The Weeknd - Secrets (Official Video)",
    "url": "https://kworb.net/youtube../video/eXDU9um19HM.html",
    "views": "207,703,243",
    "yesterday": "23,659",
    "publish": "2017/06"
  },
  {
    "title": "The Weeknd - After Hours (Audio)",
    "url": "https://kworb.net/youtube../video/ygTZZpVkmKg.html",
    "views": "201,216,344",
    "yesterday": "239,956",
    "publish": "2020/02"
  },
  {
    "title": "The Weeknd - Heartless (Official Video)",
    "url": "https://kworb.net/youtube../video/1DpH-icPpl0.html",
    "views": "196,545,614",
    "yesterday": "88,786",
    "publish": "2019/12"
  },
  {
    "title": "The Weeknd - Call Out My Name (Official Audio)",
    "url": "https://kworb.net/youtube../video/rsEne1ZiQrk.html",
    "views": "187,101,108",
    "yesterday": "161,705",
    "publish": "2018/03"
  },
  {
    "title": "The Weeknd - I Was Never There feat. Gesaffelstein (Official Audio)",
    "url": "https://kworb.net/youtube../video/OlStmta0Vh4.html",
    "views": "177,416,962",
    "yesterday": "168,816",
    "publish": "2018/03"
  },
  {
    "title": "The Weeknd - Take My Breath (Official Music Video)",
    "url": "https://kworb.net/youtube../video/rhTl_OyehF8.html",
    "views": "166,291,753",
    "yesterday": "77,956",
    "publish": "2021/08"
  },
  {
    "title": "The Weeknd - Party Monster (Official Video)",
    "url": "https://kworb.net/youtube../video/diW6jXhLE0E.html",
    "views": "162,059,523",
    "yesterday": "46,845",
    "publish": "2017/01"
  },
  {
    "title": "Maluma, The Weeknd - Hawái (Remix - Official Video)",
    "url": "https://kworb.net/youtube../video/91vECNhvmMY.html",
    "views": "160,706,448",
    "yesterday": "17,208",
    "publish": "2020/11"
  },
  {
    "title": "The Weeknd - Can’t Feel My Face (Official Audio)",
    "url": "https://kworb.net/youtube../video/dqt8Z1k0oWQ.html",
    "views": "141,135,892",
    "yesterday": "17,068",
    "publish": "2015/06"
  },
  {
    "title": "The Weeknd - In Your Eyes (Official Audio)",
    "url": "https://kworb.net/youtube../video/E3QiD99jPAg.html",
    "views": "128,835,963",
    "yesterday": "72,036",
    "publish": "2020/03"
  },
  {
    "title": "The Weeknd - M A N I A (Official Video)",
    "url": "https://kworb.net/youtube../video/kBsycvSU6r8.html",
    "views": "121,046,141",
    "yesterday": "8,233",
    "publish": "2016/11"
  },
  {
    "title": "The Weeknd - Out of Time (Official Video)",
    "url": "https://kworb.net/youtube../video/2fDzCWNS3ig.html",
    "views": "115,182,652",
    "yesterday": "100,256",
    "publish": "2022/04"
  },
  {
    "title": "Post Malone, The Weeknd - One Right Now",
    "url": "https://kworb.net/youtube../video/Tc0tLGWIqxA.html",
    "views": "113,613,204",
    "yesterday": "51,505",
    "publish": "2021/11"
  },
  {
    "title": "Swedish House Mafia and The Weeknd - Moth To A Flame (Official Video)",
    "url": "https://kworb.net/youtube../video/u9n7Cw-4_HQ.html",
    "views": "109,137,397",
    "yesterday": "150,155",
    "publish": "2021/10"
  },
  {
    "title": "The Weeknd, JENNIE & Lily Rose Depp - One Of The Girls (Official Audio)",
    "url": "https://kworb.net/youtube../video/f1r0XZLNlGQ.html",
    "views": "108,861,840",
    "yesterday": "964,287",
    "publish": "2023/06"
  },
  {
    "title": "The Weeknd - In Your Eyes (Official Video)",
    "url": "https://kworb.net/youtube../video/dqRZDebPIGs.html",
    "views": "104,193,931",
    "yesterday": "6,684",
    "publish": "2020/03"
  },
  {
    "title": "The Weeknd - Die For You (Official Music Video)",
    "url": "https://kworb.net/youtube../video/uPD0QOGTmMI.html",
    "views": "99,140,732",
    "yesterday": "146,316",
    "publish": "2021/11"
  },
  {
    "title": "The Weeknd - Starboy ft. Daft Punk (Official Lyric Video)",
    "url": "https://kworb.net/youtube../video/dMMUH_ZpbB0.html",
    "views": "95,208,094",
    "yesterday": "1,051",
    "publish": "2016/11"
  },
  {
    "title": "Juice WRLD & The Weeknd - Smile (Official Video)",
    "url": "https://kworb.net/youtube../video/2avPJ9TZNmU.html",
    "views": "94,262,875",
    "yesterday": "26,411",
    "publish": "2020/08"
  },
  {
    "title": "The Weeknd - Wicked Games",
    "url": "https://kworb.net/youtube../video/o9PuAm7d0PA.html",
    "views": "93,575,680",
    "yesterday": "23,515",
    "publish": "2011/03"
  },
  {
    "title": "The Weeknd - In The Night (Official Video)",
    "url": "https://kworb.net/youtube../video/2iFa5We6zqw.html",
    "views": "91,224,006",
    "yesterday": "6,520",
    "publish": "2015/12"
  },
  {
    "title": "The Weeknd - King Of The Fall (Official Video)",
    "url": "https://kworb.net/youtube../video/ZXBcwyMUrcU.html",
    "views": "91,221,689",
    "yesterday": "17,059",
    "publish": "2014/08"
  },
  {
    "title": "The Weeknd - Save Your Tears (Official Audio)",
    "url": "https://kworb.net/youtube../video/u6lihZAcy4s.html",
    "views": "87,327,344",
    "yesterday": "61,426",
    "publish": "2020/03"
  },
  {
    "title": "The Weeknd - Try Me (Official Audio)",
    "url": "https://kworb.net/youtube../video/y08R20KflNM.html",
    "views": "86,417,248",
    "yesterday": "40,380",
    "publish": "2018/03"
  },
  {
    "title": "The Weeknd - The Zone ft. Drake (Official Video)",
    "url": "https://kworb.net/youtube../video/tfrWuiQ4QNc.html",
    "views": "82,868,471",
    "yesterday": "8,114",
    "publish": "2012/11"
  },
  {
    "title": "The Weeknd - Tell Your Friends (Official Video)",
    "url": "https://kworb.net/youtube../video/j1ngEIxopUU.html",
    "views": "81,293,063",
    "yesterday": "9,877",
    "publish": "2015/08"
  },
  {
    "title": "The Weeknd, JENNIE, Lily-Rose Depp - One Of The Girls (Official Video)",
    "url": "https://kworb.net/youtube../video/Mx92lTYxrJQ.html",
    "views": "79,836,576",
    "yesterday": "677,166",
    "publish": "2023/07"
  },
  {
    "title": "Ariana Grande, The Weeknd - Love Me Harder (Official Lyric Video)",
    "url": "https://kworb.net/youtube../video/szGomck3sZI.html",
    "views": "78,208,449",
    "yesterday": "13,388",
    "publish": "2014/10"
  },
  {
    "title": "NAV - Some Way ft. The Weeknd (Official Music Video)",
    "url": "https://kworb.net/youtube../video/MRLyREkZles.html",
    "views": "76,896,030",
    "yesterday": "7,293",
    "publish": "2017/03"
  },
  {
    "title": "The Weeknd - High For This",
    "url": "https://kworb.net/youtube../video/sX9DgavXiN4.html",
    "views": "76,715,391",
    "yesterday": "5,355",
    "publish": "2011/03"
  },
  {
    "title": "The Weeknd - Hurt You feat. Gesaffelstein (Official Audio)",
    "url": "https://kworb.net/youtube../video/wKDU5pXhf5o.html",
    "views": "71,118,836",
    "yesterday": "26,519",
    "publish": "2018/03"
  },
  {
    "title": "The Weeknd - Is There Someone Else? (Audio)",
    "url": "https://kworb.net/youtube../video/i4ZuseKFBF0.html",
    "views": "71,021,303",
    "yesterday": "130,674",
    "publish": "2022/01"
  },
  {
    "title": "The Weeknd, Kendrick Lamar - Pray For Me (Audio)",
    "url": "https://kworb.net/youtube../video/K5xERXE7pxI.html",
    "views": "68,337,556",
    "yesterday": "2,355",
    "publish": "2018/02"
  },
  {
    "title": "The Weeknd - In The Night (Official Audio)",
    "url": "https://kworb.net/youtube../video/9CbQl98JEbE.html",
    "views": "67,599,657",
    "yesterday": "19,810",
    "publish": "2016/02"
  },
  {
    "title": "The Weeknd - Save Your Tears / In Your Eyes (Live on The 2020 American Music Awards)",
    "url": "https://kworb.net/youtube../video/f-g_SHNv5NI.html",
    "views": "66,750,785",
    "yesterday": "11,519",
    "publish": "2020/11"
  },
  {
    "title": "The Weeknd - Sacrifice",
    "url": "https://kworb.net/youtube../video/VafTMsrnSTU.html",
    "views": "66,132,035",
    "yesterday": "32,079",
    "publish": "2022/01"
  },
  {
    "title": "The Weeknd - The Morning",
    "url": "https://kworb.net/youtube../video/5TAko3RH0bk.html",
    "views": "62,260,084",
    "yesterday": "23,067",
    "publish": "2011/03"
  },
  {
    "title": "Juicy J - One of Those Nights ft. The Weeknd (Explicit) [Official Video]",
    "url": "https://kworb.net/youtube../video/VP7GNxLI9fM.html",
    "views": "62,006,063",
    "yesterday": "9,771",
    "publish": "2013/06"
  },
  {
    "title": "The Weeknd - Wasted Times (Official Audio)",
    "url": "https://kworb.net/youtube../video/R0rKB_bsUNg.html",
    "views": "60,759,602",
    "yesterday": "16,266",
    "publish": "2018/03"
  },
  {
    "title": "The Weeknd, Madonna, Playboi Carti - Popular (Visualizer)",
    "url": "https://kworb.net/youtube../video/xnvkStb2jT0.html",
    "views": "56,392,891",
    "yesterday": "178,352",
    "publish": "2023/06"
  },
  {
    "title": "The Weeknd - Rolling Stone (Explicit) (Official Video)",
    "url": "https://kworb.net/youtube../video/ORVz_qeKgvg.html",
    "views": "53,922,403",
    "yesterday": "5,987",
    "publish": "2012/10"
  },
  {
    "title": "The Weeknd \"Earned It\" (Fifty Shades Of Grey) Official Lyric Video",
    "url": "https://kworb.net/youtube../video/NdDeWJRWsqY.html",
    "views": "53,187,522",
    "yesterday": "3,622",
    "publish": "2014/12"
  },
  {
    "title": "The Weeknd ft. ROSALÍA - Blinding Lights [Remix] (Official Lyric Video)",
    "url": "https://kworb.net/youtube../video/Soly0ne467M.html",
    "views": "49,775,337",
    "yesterday": "4,399",
    "publish": "2020/12"
  },
  {
    "title": "The Weeknd - Die For You (Official Audio)",
    "url": "https://kworb.net/youtube../video/RpyN9pFXUCg.html",
    "views": "46,800,826",
    "yesterday": "1,263",
    "publish": "2021/02"
  },
  {
    "title": "The Weeknd - Heartless (Official Audio)",
    "url": "https://kworb.net/youtube../video/-uj9b9JCIJM.html",
    "views": "45,965,836",
    "yesterday": "19,210",
    "publish": "2019/11"
  },
  {
    "title": "The Weeknd - Trust Issues (Remix)",
    "url": "https://kworb.net/youtube../video/YVCV6hyv7ac.html",
    "views": "45,637,248",
    "yesterday": "63,646",
    "publish": "2011/06"
  },
  {
    "title": "The Weeknd - Starboy (Audio) ft. Daft Punk",
    "url": "https://kworb.net/youtube../video/Rif-RTvmmss.html",
    "views": "44,042,861",
    "yesterday": "123,228",
    "publish": "2023/03"
  },
  {
    "title": "The Weeknd - Blinding Lights (Live On The 2020 MTV VMAs)",
    "url": "https://kworb.net/youtube../video/ewfdRy5jfF8.html",
    "views": "42,759,201",
    "yesterday": "16,647",
    "publish": "2020/09"
  },
  {
    "title": "The Weeknd - What You Need",
    "url": "https://kworb.net/youtube../video/PGCVhhUxnp8.html",
    "views": "41,318,639",
    "yesterday": "22,585",
    "publish": "2011/02"
  },
  {
    "title": "Wiz Khalifa - Remember You ft. The Weeknd [Official Video]",
    "url": "https://kworb.net/youtube../video/URdf7WX-nlc.html",
    "views": "40,947,534",
    "yesterday": "5,899",
    "publish": "2012/11"
  },
  {
    "title": "SZA, The Weeknd, Travis Scott - Power Is Power (Official Video)",
    "url": "https://kworb.net/youtube../video/IfCuarZqJzM.html",
    "views": "40,840,307",
    "yesterday": "10,807",
    "publish": "2019/05"
  },
  {
    "title": "The Weeknd - Is There Someone Else?",
    "url": "https://kworb.net/youtube../video/1XqIWr_WqM4.html",
    "views": "40,671,221",
    "yesterday": "79,798",
    "publish": "2023/01"
  },
  {
    "title": "The Weeknd - House Of Balloons / Glass Table Girls",
    "url": "https://kworb.net/youtube../video/8ex38L8xtNI.html",
    "views": "39,028,105",
    "yesterday": "61,992",
    "publish": "2011/03"
  },
  {
    "title": "The Weeknd - In Your Eyes Remix feat. Doja Cat (Audio)",
    "url": "https://kworb.net/youtube../video/ozMBCFd7fFM.html",
    "views": "38,728,509",
    "yesterday": "10,918",
    "publish": "2020/05"
  },
  {
    "title": "The Weeknd - Next",
    "url": "https://kworb.net/youtube../video/-iW1-BuJ_Hc.html",
    "views": "37,704,141",
    "yesterday": "6,471",
    "publish": "2012/01"
  },
  {
    "title": "Wiz Khalifa - Remember You ft. The Weeknd [Audio]",
    "url": "https://kworb.net/youtube../video/WBGbYagI6G4.html",
    "views": "37,266,694",
    "yesterday": "2,793",
    "publish": "2012/09"
  },
  {
    "title": "The Weeknd - Live For ft. Drake (Explicit) (Official Video)",
    "url": "https://kworb.net/youtube../video/GLr0usOC2_k.html",
    "views": "36,339,232",
    "yesterday": "1,586",
    "publish": "2013/09"
  },
  {
    "title": "The Weeknd ft. Future - Double Fantasy (Official Music Video)",
    "url": "https://kworb.net/youtube../video/dMoFcvfd5t4.html",
    "views": "34,691,423",
    "yesterday": "50,164",
    "publish": "2023/04"
  },
  {
    "title": "French Montana - A Lie (Official Video) ft. The Weeknd, Max B",
    "url": "https://kworb.net/youtube../video/tPZbBBdfr5E.html",
    "views": "34,148,765",
    "yesterday": "625",
    "publish": "2017/07"
  },
  {
    "title": "The Weeknd, Playboi Carti, Madonna - Popular (Official Audio)",
    "url": "https://kworb.net/youtube../video/K6WCcBP4lSs.html",
    "views": "32,986,355",
    "yesterday": "96,283",
    "publish": "2023/06"
  },
  {
    "title": "The Weeknd - Reminder (Audio)",
    "url": "https://kworb.net/youtube../video/h_VCgsWLmY4.html",
    "views": "30,275,229",
    "yesterday": "92,033",
    "publish": "2023/03"
  },
  {
    "title": "The Weeknd - Nothing Is Lost (You Give Me Strength) (Official Lyric Video)",
    "url": "https://kworb.net/youtube../video/bDHD1ueL4a4.html",
    "views": "30,092,245",
    "yesterday": "14,905",
    "publish": "2022/12"
  },
  {
    "title": "The Weeknd - The Zone (feat. Drake)",
    "url": "https://kworb.net/youtube../video/YWIhwplfx4Q.html",
    "views": "29,403,186",
    "yesterday": "5,280",
    "publish": "2011/08"
  },
  {
    "title": "Lana Del Rey - Lust For Life ft. The Weeknd (Official Audio)",
    "url": "https://kworb.net/youtube../video/35cTIXoBnuw.html",
    "views": "27,642,171",
    "yesterday": "118",
    "publish": "2017/04"
  },
  {
    "title": "The Weeknd - The Weeknd – Save Your Tears (Live on The 2021 Billboard Music Awards)",
    "url": "https://kworb.net/youtube../video/-Ot0vHUyEpw.html",
    "views": "27,424,065",
    "yesterday": "8,273",
    "publish": "2021/05"
  },
  {
    "title": "The Weeknd - Snowchild (Animated Video)",
    "url": "https://kworb.net/youtube../video/G0JKdFjWkLA.html",
    "views": "27,394,371",
    "yesterday": "7,863",
    "publish": "2020/07"
  },
  {
    "title": "The Weeknd - Too Late (Audio)",
    "url": "https://kworb.net/youtube../video/nl71vFvVOvw.html",
    "views": "26,828,467",
    "yesterday": "12,973",
    "publish": "2020/03"
  },
  {
    "title": "Ariana Grande, The Weeknd - Love Me Harder (Acoustic)",
    "url": "https://kworb.net/youtube../video/DVnz9iyolLA.html",
    "views": "26,511,511",
    "yesterday": "2,664",
    "publish": "2015/01"
  },
  {
    "title": "The Weeknd - Out of Time (Audio)",
    "url": "https://kworb.net/youtube../video/kxgj5af8zg4.html",
    "views": "26,449,839",
    "yesterday": "26,983",
    "publish": "2022/01"
  },
  {
    "title": "The Weeknd - Escape From LA (Audio)",
    "url": "https://kworb.net/youtube../video/vsARlcGW0jE.html",
    "views": "26,201,794",
    "yesterday": "8,229",
    "publish": "2020/03"
  },
  {
    "title": "The Weeknd - Less Than Zero (Official Lyric Video)",
    "url": "https://kworb.net/youtube../video/UKunvvN2iCk.html",
    "views": "25,088,780",
    "yesterday": "24,875",
    "publish": "2022/01"
  },
  {
    "title": "The Weeknd - Alone Again (Official Audio)",
    "url": "https://kworb.net/youtube../video/JH398xAYpZA.html",
    "views": "25,046,905",
    "yesterday": "8,558",
    "publish": "2020/03"
  },
  {
    "title": "The Weeknd - Privilege (Official Audio)",
    "url": "https://kworb.net/youtube../video/JcVDXHeD59c.html",
    "views": "24,584,765",
    "yesterday": "7,962",
    "publish": "2018/03"
  },
  {
    "title": "The Weeknd - Faith (Audio)",
    "url": "https://kworb.net/youtube../video/RcS_8-a-sMg.html",
    "views": "24,225,744",
    "yesterday": "8,401",
    "publish": "2020/03"
  },
  {
    "title": "The Weeknd - Belong To The World (Official Video)",
    "url": "https://kworb.net/youtube../video/lYO77zNhWl4.html",
    "views": "23,960,833",
    "yesterday": "1,910",
    "publish": "2013/07"
  },
  {
    "title": "The Weeknd - In Your Eyes (iHeartRadio Jingle Ball Live Performance)",
    "url": "https://kworb.net/youtube../video/Xe6-2yJJkk0.html",
    "views": "23,071,983",
    "yesterday": "9,635",
    "publish": "2020/12"
  },
  {
    "title": "The Weeknd - Until I Bleed Out (Official Video)",
    "url": "https://kworb.net/youtube../video/i58MNnk6BhY.html",
    "views": "22,711,160",
    "yesterday": "7,691",
    "publish": "2020/04"
  },
  {
    "title": "The Weeknd - The Party & The After Party",
    "url": "https://kworb.net/youtube../video/yI-zb_aP0So.html",
    "views": "22,304,906",
    "yesterday": "12,943",
    "publish": "2011/03"
  },
  {
    "title": "The Weeknd - Save Your Tears (iHeartRadio Jingle Ball Live Performance)",
    "url": "https://kworb.net/youtube../video/mAcQRgPWZDE.html",
    "views": "22,264,804",
    "yesterday": "11,519",
    "publish": "2020/12"
  },
  {
    "title": "The Weeknd - Secrets/Can’t Feel My Face (Vevo Presents)",
    "url": "https://kworb.net/youtube../video/NaTGwlfRB_c.html",
    "views": "21,892,480",
    "yesterday": "1,396",
    "publish": "2016/12"
  },
  {
    "title": "The Weeknd, Madonna, Playboi Carti - Popular (Official Music Video)",
    "url": "https://kworb.net/youtube../video/vt0i6nuqNEo.html",
    "views": "21,527,118",
    "yesterday": "582,234",
    "publish": "2024/02"
  },
  {
    "title": "The Weeknd - Less Than Zero (Audio)",
    "url": "https://kworb.net/youtube../video/LKsgDcckur0.html",
    "views": "21,330,422",
    "yesterday": "22,853",
    "publish": "2022/01"
  },
  {
    "title": "The Weeknd - Too Late (Official Video)",
    "url": "https://kworb.net/youtube../video/Wh8DT09QCHI.html",
    "views": "21,029,969",
    "yesterday": "1,704",
    "publish": "2020/10"
  },
  {
    "title": "The Weeknd - Coming Down",
    "url": "https://kworb.net/youtube../video/WVg1mbxTkFo.html",
    "views": "20,846,834",
    "yesterday": "59,887",
    "publish": "2011/03"
  },
  {
    "title": "The Weeknd - Loft Music",
    "url": "https://kworb.net/youtube../video/HOdNMwTNNhA.html",
    "views": "19,566,219",
    "yesterday": "3,198",
    "publish": "2011/03"
  },
  {
    "title": "The Weeknd - Try Me (Official Video)",
    "url": "https://kworb.net/youtube../video/2DjM0lY4pbE.html",
    "views": "19,072,411",
    "yesterday": "19,073",
    "publish": "2021/03"
  },
  {
    "title": "The Weeknd - Save Your Tears (The Tik Tok Experience)",
    "url": "https://kworb.net/youtube../video/Fj_7w5Km0ZY.html",
    "views": "18,549,008",
    "yesterday": "474",
    "publish": "2020/08"
  },
  {
    "title": "The Weeknd - Hardest To Love (Audio)",
    "url": "https://kworb.net/youtube../video/pM3nIOYF2W8.html",
    "views": "18,339,785",
    "yesterday": "7,625",
    "publish": "2020/03"
  },
  {
    "title": "The Weeknd - Gasoline (Official Music Video)",
    "url": "https://kworb.net/youtube../video/iOa7uE23qc4.html",
    "views": "17,649,955",
    "yesterday": "6,662",
    "publish": "2022/01"
  },
  {
    "title": "The Weeknd - Acquainted (Official Audio)",
    "url": "https://kworb.net/youtube../video/-OMptcPcw0Y.html",
    "views": "16,675,834",
    "yesterday": "23,509",
    "publish": "2021/02"
  },
  {
    "title": "The Weeknd - Call Out My Name (Official Lyric Video)",
    "url": "https://kworb.net/youtube../video/J3vav5Sfhrw.html",
    "views": "16,615,648",
    "yesterday": "508",
    "publish": "2018/04"
  },
  {
    "title": "The Weeknd - Save Your Tears (Live at The BRIT Awards 2021)",
    "url": "https://kworb.net/youtube../video/iKm5-XtXcII.html",
    "views": "16,403,003",
    "yesterday": "2,309",
    "publish": "2021/05"
  },
  {
    "title": "American Dad — The Weeknd’s Dark Secret",
    "url": "https://kworb.net/youtube../video/S7OTZMopkUg.html",
    "views": "16,121,038",
    "yesterday": "1,004",
    "publish": "2020/05"
  },
  {
    "title": "The Weeknd - In Your Eyes (Remix / Animated) ft. Doja Cat",
    "url": "https://kworb.net/youtube../video/QeRsc6pqdEM.html",
    "views": "15,819,784",
    "yesterday": "1,209",
    "publish": "2020/07"
  },
  {
    "title": "The Weeknd - Intro/Starboy (Live from Vevo Presents)",
    "url": "https://kworb.net/youtube../video/SsRXJnzas2s.html",
    "views": "15,807,695",
    "yesterday": "2,821",
    "publish": "2016/12"
  },
  {
    "title": "The Weeknd - Twenty Eight (Explicit) (Official Video)",
    "url": "https://kworb.net/youtube../video/2_ScGcuXZqc.html",
    "views": "15,485,489",
    "yesterday": "3,365",
    "publish": "2013/02"
  },
  {
    "title": "The Weeknd, Lily Rose Depp & Ramsey - Fill the Void (Official Audio)",
    "url": "https://kworb.net/youtube../video/2QMyW1LZBBM.html",
    "views": "15,275,441",
    "yesterday": "61,525",
    "publish": "2023/06"
  },
  {
    "title": "The Weeknd - Blinding Lights (Live On Jimmy Kimmel Live! / 2020)",
    "url": "https://kworb.net/youtube../video/VJYpyC1SNPc.html",
    "views": "15,190,302",
    "yesterday": "1,433",
    "publish": "2020/01"
  },
  {
    "title": "The Weeknd - Montreal",
    "url": "https://kworb.net/youtube../video/TV1r4m8c9SI.html",
    "views": "15,183,526",
    "yesterday": "5,216",
    "publish": "2011/12"
  },
  {
    "title": "The Weeknd - How Do I Make You Love Me? (Official Music Video)",
    "url": "https://kworb.net/youtube../video/VLMo0rthnoo.html",
    "views": "14,540,717",
    "yesterday": "7,503",
    "publish": "2022/07"
  },
  {
    "title": "The Weeknd - 103.5 DAWN FM",
    "url": "https://kworb.net/youtube../video/hWlYEaxubRY.html",
    "views": "14,539,712",
    "yesterday": "9,112",
    "publish": "2022/01"
  },
  {
    "title": "The Weeknd - The Birds (Part 1)",
    "url": "https://kworb.net/youtube../video/t2_YyRBYZjM.html",
    "views": "14,101,271",
    "yesterday": "3,509",
    "publish": "2011/06"
  },
  {
    "title": "The Weeknd - After Hours (Short Film)",
    "url": "https://kworb.net/youtube../video/oq9AgxHvGjw.html",
    "views": "14,081,769",
    "yesterday": "4,163",
    "publish": "2020/03"
  },
  {
    "title": "The Weeknd - Gone",
    "url": "https://kworb.net/youtube../video/CqHKfscXS64.html",
    "views": "13,488,263",
    "yesterday": "1,893",
    "publish": "2011/08"
  },
  {
    "title": "Lily-Rose Depp - World Class Sinner / I’m a Freak (Official Audio)",
    "url": "https://kworb.net/youtube../video/CD90Zx1BYiQ.html",
    "views": "13,474,613",
    "yesterday": "17,760",
    "publish": "2023/06"
  },
  {
    "title": "The Weeknd - Same Old Song",
    "url": "https://kworb.net/youtube../video/NID-2orTN8U.html",
    "views": "13,314,193",
    "yesterday": "3,528",
    "publish": "2012/01"
  },
  {
    "title": "The Weeknd - Outside",
    "url": "https://kworb.net/youtube../video/umvomiY7804.html",
    "views": "12,860,581",
    "yesterday": "2,697",
    "publish": "2011/12"
  },
  {
    "title": "The Weeknd - Alone Again (Official Live Performance)",
    "url": "https://kworb.net/youtube../video/8JrpOFWczLs.html",
    "views": "12,326,725",
    "yesterday": "4,890",
    "publish": "2020/11"
  },
  {
    "title": "The Weeknd - The Hills (Live at Apple Music Festival: London 2015)",
    "url": "https://kworb.net/youtube../video/NZXb_N4mCL0.html",
    "views": "12,216,323",
    "yesterday": "2,582",
    "publish": "2015/10"
  },
  {
    "title": "The Weeknd, Swedish House Mafia - Sacrifice (Remix / Alternate World)",
    "url": "https://kworb.net/youtube../video/lu7lJ5okjyo.html",
    "views": "12,155,734",
    "yesterday": "4,226",
    "publish": "2022/01"
  },
  {
    "title": "The Weeknd - The Knowing",
    "url": "https://kworb.net/youtube../video/WsdmtOYtxNk.html",
    "views": "12,155,253",
    "yesterday": "2,599",
    "publish": "2011/03"
  },
  {
    "title": "The Weeknd - Sidewalks ft. Kendrick Lamar (Vevo Presents)",
    "url": "https://kworb.net/youtube../video/uxBganA7KnY.html",
    "views": "12,121,117",
    "yesterday": "841",
    "publish": "2016/12"
  },
  {
    "title": "The Weeknd - Party Monster (Vevo Presents)",
    "url": "https://kworb.net/youtube../video/lysp-BVbf9Q.html",
    "views": "12,002,593",
    "yesterday": "737",
    "publish": "2016/12"
  },
  {
    "title": "The Weeknd - Scared To Live (Audio)",
    "url": "https://kworb.net/youtube../video/MzsU_sn2aIE.html",
    "views": "11,996,897",
    "yesterday": "3,864",
    "publish": "2020/03"
  },
  {
    "title": "The Weeknd - Blinding Lights (Official Lyric Video)",
    "url": "https://kworb.net/youtube../video/o6ytLPKscrU.html",
    "views": "11,920,788",
    "yesterday": "305",
    "publish": "2019/12"
  },
  {
    "title": "The Weeknd - Take My Breath (Official Audio)",
    "url": "https://kworb.net/youtube../video/eT1E3gmST9U.html",
    "views": "11,308,105",
    "yesterday": "10,532",
    "publish": "2021/08"
  },
  {
    "title": "The Weeknd - Pretty (Explicit) (Official Video)",
    "url": "https://kworb.net/youtube../video/HxilwT1sKSo.html",
    "views": "11,133,492",
    "yesterday": "1,302",
    "publish": "2013/09"
  },
  {
    "title": "The Weeknd - Kiss Land",
    "url": "https://kworb.net/youtube../video/eN84vAqO9NY.html",
    "views": "11,035,234",
    "yesterday": "180",
    "publish": "2013/05"
  },
  {
    "title": "The Weeknd - The Birds (Part 2)",
    "url": "https://kworb.net/youtube../video/9FE-Pwm2cyc.html",
    "views": "10,782,334",
    "yesterday": "3,120",
    "publish": "2011/08"
  },
  {
    "title": "The Weeknd - Is There Someone Else? (Official LyricVideo)",
    "url": "https://kworb.net/youtube../video/b-esdxjN8N8.html",
    "views": "10,728,551",
    "yesterday": "4,920",
    "publish": "2022/01"
  },
  {
    "title": "The Weeknd - Lonely Star",
    "url": "https://kworb.net/youtube../video/pdH1kXzquQo.html",
    "views": "10,505,442",
    "yesterday": "2,018",
    "publish": "2011/08"
  },
  {
    "title": "The Weeknd - Coachella 2022 (Full Set)",
    "url": "https://kworb.net/youtube../video/L8ZoGtAQ1mw.html",
    "views": "10,476,513",
    "yesterday": "7,377",
    "publish": "2022/05"
  },
  {
    "title": "The Weeknd - Reminder (Vevo Presents)",
    "url": "https://kworb.net/youtube../video/yhNQAAMCKms.html",
    "views": "10,449,289",
    "yesterday": "1,763",
    "publish": "2016/12"
  },
  {
    "title": "The Weeknd - XO / The Host",
    "url": "https://kworb.net/youtube../video/6FFSCF0gXt0.html",
    "views": "10,367,644",
    "yesterday": "3,141",
    "publish": "2011/12"
  },
  {
    "title": "The Weeknd - The Hills (Vevo Presents)",
    "url": "https://kworb.net/youtube../video/hTaihFTiXgc.html",
    "views": "10,321,761",
    "yesterday": "1,228",
    "publish": "2016/12"
  },
  {
    "title": "The Weeknd - The Knowing (Official Video)",
    "url": "https://kworb.net/youtube../video/vPp5Ty9EE6k.html",
    "views": "9,554,697",
    "yesterday": "1,917",
    "publish": "2012/02"
  },
  {
    "title": "The Weeknd - Out Of Time (Official Lyric Video)",
    "url": "https://kworb.net/youtube../video/xBa3YUgQeL4.html",
    "views": "9,427,164",
    "yesterday": "3,354",
    "publish": "2022/01"
  },
  {
    "title": "The Weeknd - Starboy ft. Daft Punk (Live on SNL)",
    "url": "https://kworb.net/youtube../video/IllxqeXh8Go.html",
    "views": "9,419,144",
    "yesterday": "472",
    "publish": "2016/10"
  },
  {
    "title": "The Weeknd - D.D.",
    "url": "https://kworb.net/youtube../video/FXT1oKrgq0o.html",
    "views": "9,375,415",
    "yesterday": "3,864",
    "publish": "2011/12"
  },
  {
    "title": "The Weeknd - Blinding Lights (The Tik Tok Experience) ft. Major Lazer",
    "url": "https://kworb.net/youtube../video/uViueiV8fME.html",
    "views": "9,347,547",
    "yesterday": "940",
    "publish": "2020/08"
  },
  {
    "title": "The Weeknd - Starboy ft. Daft Punk (Live On The Voice Season 11)",
    "url": "https://kworb.net/youtube../video/FPAmeM3JJQk.html",
    "views": "9,309,402",
    "yesterday": "639",
    "publish": "2016/12"
  },
  {
    "title": "The Weeknd - Die For You (Audio)",
    "url": "https://kworb.net/youtube../video/2AH5l-vrY9Q.html",
    "views": "9,204,543",
    "yesterday": "26,070",
    "publish": "2023/03"
  },
  {
    "title": "The Weeknd - Sacrifice (Audio)",
    "url": "https://kworb.net/youtube../video/E6zblNbGXA4.html",
    "views": "9,103,664",
    "yesterday": "10,253",
    "publish": "2022/01"
  },
  {
    "title": "The Weeknd - Thursday",
    "url": "https://kworb.net/youtube../video/0Suprl56Owg.html",
    "views": "9,024,753",
    "yesterday": "1,375",
    "publish": "2011/08"
  },
  {
    "title": "The Weeknd - Snowchild (Audio)",
    "url": "https://kworb.net/youtube../video/UxPEFFHA4xw.html",
    "views": "9,012,732",
    "yesterday": "1,314",
    "publish": "2020/03"
  },
  {
    "title": "The Weeknd - Blinding Lights (Chromatics Remix Music Video)",
    "url": "https://kworb.net/youtube../video/imOUKPruPHk.html",
    "views": "8,790,880",
    "yesterday": "1,017",
    "publish": "2020/05"
  },
  {
    "title": "The Weeknd - Take My Breath (Remix) ft. Agents of Time",
    "url": "https://kworb.net/youtube../video/43QiQfhFToY.html",
    "views": "8,723,144",
    "yesterday": "3,137",
    "publish": "2022/01"
  },
  {
    "title": "The Weeknd - Party Monster (Audio)",
    "url": "https://kworb.net/youtube../video/j9Hije4z6O4.html",
    "views": "8,716,459",
    "yesterday": "31,040",
    "publish": "2023/03"
  },
  {
    "title": "The Weeknd - Faith (Official Live Performance) | Vevo",
    "url": "https://kworb.net/youtube../video/8xH0sdjMINY.html",
    "views": "8,569,317",
    "yesterday": "3,260",
    "publish": "2020/11"
  },
  {
    "title": "The Weeknd - Initiation",
    "url": "https://kworb.net/youtube../video/EDFEQyx7o4k.html",
    "views": "8,384,047",
    "yesterday": "1,951",
    "publish": "2012/01"
  },
  {
    "title": "The Weeknd - Rolling Stone",
    "url": "https://kworb.net/youtube../video/fCPkgAIANys.html",
    "views": "8,362,685",
    "yesterday": "386",
    "publish": "2011/05"
  },
  {
    "title": "The Weeknd - Gasoline (Audio)",
    "url": "https://kworb.net/youtube../video/0T4UykXuJnI.html",
    "views": "8,061,991",
    "yesterday": "6,855",
    "publish": "2022/01"
  },
  {
    "title": "The Weeknd - In The Night (Short Version) (Official Video)",
    "url": "https://kworb.net/youtube../video/tsUmC5ulukc.html",
    "views": "8,018,187",
    "yesterday": "246",
    "publish": "2016/02"
  },
  {
    "title": "The Weeknd - Blinding Lights (Behind The Scenes)",
    "url": "https://kworb.net/youtube../video/ycdFpM3njTs.html",
    "views": "7,927,999",
    "yesterday": "1,303",
    "publish": "2020/02"
  },
  {
    "title": "The Weeknd - I Heard You’re Married (Audio) ft. Lil Wayne",
    "url": "https://kworb.net/youtube../video/srxa-cWPJTo.html",
    "views": "7,702,748",
    "yesterday": "3,458",
    "publish": "2022/01"
  },
  {
    "title": "The Weeknd ft. Future - Double Fantasy (Official Audio)",
    "url": "https://kworb.net/youtube../video/DQnBal7mVtE.html",
    "views": "7,613,705",
    "yesterday": "19,618",
    "publish": "2023/04"
  },
  {
    "title": "The Weeknd - The Fall",
    "url": "https://kworb.net/youtube../video/YK9N-Xh32eE.html",
    "views": "7,430,195",
    "yesterday": "1,758",
    "publish": "2012/01"
  },
  {
    "title": "The Weeknd - Heartless (Live on The Late Show with Stephen Colbert / 2019)",
    "url": "https://kworb.net/youtube../video/MebxOSsP6yk.html",
    "views": "7,117,020",
    "yesterday": "1,112",
    "publish": "2020/01"
  },
  {
    "title": "The Weeknd - Repeat After Me (Interlude) (Audio)",
    "url": "https://kworb.net/youtube../video/CE-Iy24NOTY.html",
    "views": "6,916,029",
    "yesterday": "2,991",
    "publish": "2020/03"
  },
  {
    "title": "The Weeknd - Stargirl Interlude (Audio) ft. Lana Del Rey",
    "url": "https://kworb.net/youtube../video/TkxVOa6u59M.html",
    "views": "6,821,855",
    "yesterday": "31,580",
    "publish": "2023/03"
  },
  {
    "title": "The Weeknd - \"Blinding Lights\" (Live on Saturday Night Live / 2020)",
    "url": "https://kworb.net/youtube../video/17GxpgE-Fwo.html",
    "views": "6,799,910",
    "yesterday": "675",
    "publish": "2020/03"
  },
  {
    "title": "The Weeknd - Blinding Lights (iHeartRadio Jingle Ball Live Performance)",
    "url": "https://kworb.net/youtube../video/hNYkP0XHHYY.html",
    "views": "6,782,018",
    "yesterday": "3,478",
    "publish": "2020/12"
  },
  {
    "title": "The Weeknd - Dawn FM (Audio)",
    "url": "https://kworb.net/youtube../video/w8eFZoOcYKc.html",
    "views": "6,641,425",
    "yesterday": "3,036",
    "publish": "2022/01"
  },
  {
    "title": "The Weeknd - Echoes Of Silence",
    "url": "https://kworb.net/youtube../video/rtLBud9zPF0.html",
    "views": "6,539,278",
    "yesterday": "657",
    "publish": "2012/01"
  },
  {
    "title": "The Weeknd - In Your Eyes ft. Kenny G (Official Live Performance) | Vevo",
    "url": "https://kworb.net/youtube../video/-YTgFUNwRKk.html",
    "views": "6,273,778",
    "yesterday": "2,461",
    "publish": "2020/11"
  },
  {
    "title": "The Weeknd - The Zone feat. Drake (Official Video)",
    "url": "https://kworb.net/youtube../video/HqyBbd2ZMBw.html",
    "views": "6,033,630",
    "yesterday": "168",
    "publish": "2012/11"
  },
  {
    "title": "The Weeknd - Take My Breath (Official Lyric Video)",
    "url": "https://kworb.net/youtube../video/oH1eiyQpw2E.html",
    "views": "5,885,462",
    "yesterday": "488",
    "publish": "2021/08"
  },
  {
    "title": "The Weeknd - False Alarm (Live on SNL)",
    "url": "https://kworb.net/youtube../video/q24MOFOscH4.html",
    "views": "5,757,451",
    "yesterday": "296",
    "publish": "2016/10"
  },
  {
    "title": "The Weeknd - How Do I Make You Love Me? (Audio)",
    "url": "https://kworb.net/youtube../video/IB_FP_rEih4.html",
    "views": "5,740,964",
    "yesterday": "2,607",
    "publish": "2022/01"
  },
  {
    "title": "The Weeknd - How Do I Make You Love Me? (Official LyricVideo)",
    "url": "https://kworb.net/youtube../video/g4tHn1Ng_iM.html",
    "views": "5,679,201",
    "yesterday": "3,246",
    "publish": "2022/01"
  },
  {
    "title": "The Weeknd - \"Scared To Live\" (Live on Saturday Night Live / 2020)",
    "url": "https://kworb.net/youtube../video/6Nm9RZqBaBM.html",
    "views": "5,617,459",
    "yesterday": "797",
    "publish": "2020/03"
  },
  {
    "title": "The Weeknd - Best Friends (Audio)",
    "url": "https://kworb.net/youtube../video/jkEzNvdKGeA.html",
    "views": "5,563,064",
    "yesterday": "3,701",
    "publish": "2022/01"
  },
  {
    "title": "The Weeknd - The Hills (Live at The BRIT Awards 2016)",
    "url": "https://kworb.net/youtube../video/rZHLmOVQ6RA.html",
    "views": "5,536,381",
    "yesterday": "177",
    "publish": "2016/02"
  },
  {
    "title": "The Weeknd - The Morning (Official Audio)",
    "url": "https://kworb.net/youtube../video/uac4q389yaM.html",
    "views": "5,467,964",
    "yesterday": "2,652",
    "publish": "2021/02"
  },
  {
    "title": "The Weeknd, Playboi Carti, Madonna - Popular (Official Live)",
    "url": "https://kworb.net/youtube../video/bLRuz63w_SM.html",
    "views": "5,118,125",
    "yesterday": "9,678",
    "publish": "2023/07"
  },
  {
    "title": "The Weeknd - In Your Eyes ft Kenny G (Time100 Live Performance)",
    "url": "https://kworb.net/youtube../video/I3f05qYeVl8.html",
    "views": "4,969,167",
    "yesterday": "508",
    "publish": "2020/09"
  },
  {
    "title": "The Weeknd - The Hills (Vevo Presents)",
    "url": "https://kworb.net/youtube../video/Yg7JqhmAaUs.html",
    "views": "4,968,411",
    "yesterday": "103",
    "publish": "2015/08"
  },
  {
    "title": "The Weeknd - Can't Feel My Face (Martin Garrix Remix)",
    "url": "https://kworb.net/youtube../video/6CnP8ghhZPQ.html",
    "views": "4,910,917",
    "yesterday": "509",
    "publish": "2015/11"
  },
  {
    "title": "The Weeknd - Kiss Land (Official Video)",
    "url": "https://kworb.net/youtube../video/Wq6V9YpE1aE.html",
    "views": "4,805,224",
    "yesterday": "1,614",
    "publish": "2013/06"
  },
  {
    "title": "Nothing Is Lost (You Give Me Strength) (From \"Avatar: The Way of Water\"/Soundtrack Vers...",
    "url": "https://kworb.net/youtube../video/8f3HbKyaEtk.html",
    "views": "4,625,686",
    "yesterday": "2,889",
    "publish": "2023/01"
  },
  {
    "title": "The Weeknd - Best Friends (Official Lyric Video)",
    "url": "https://kworb.net/youtube../video/hpNBXbJ7rzs.html",
    "views": "4,617,804",
    "yesterday": "2,713",
    "publish": "2022/01"
  },
  {
    "title": "The Weeknd - Blinding Lights (Official Instrumental)",
    "url": "https://kworb.net/youtube../video/XajaJYraODs.html",
    "views": "4,532,576",
    "yesterday": "1,691",
    "publish": "2020/10"
  },
  {
    "title": "The Weeknd - Nothing Is Lost (You Give Me Strength) (Official Visualizer)",
    "url": "https://kworb.net/youtube../video/BkeAbsqvtVo.html",
    "views": "4,499,352",
    "yesterday": "3,520",
    "publish": "2022/12"
  },
  {
    "title": "The Weeknd - Blinding Lights (Time100 Live Performance)",
    "url": "https://kworb.net/youtube../video/c2odnv29TlU.html",
    "views": "4,382,135",
    "yesterday": "269",
    "publish": "2020/09"
  },
  {
    "title": "The Weeknd ft. Lil Wayne - I Heard You're Married (Official Lyric Video)",
    "url": "https://kworb.net/youtube../video/86kEbw4pvxU.html",
    "views": "4,327,374",
    "yesterday": "2,642",
    "publish": "2022/01"
  },
  {
    "title": "The Weeknd - Life Of The Party",
    "url": "https://kworb.net/youtube../video/_bSXY75R3Wc.html",
    "views": "4,291,763",
    "yesterday": "1,224",
    "publish": "2011/08"
  },
  {
    "title": "The Weeknd - In Your Eyes (Remix / Audio) ft. Kenny G",
    "url": "https://kworb.net/youtube../video/0NiL4Vpjju4.html",
    "views": "4,251,905",
    "yesterday": "793",
    "publish": "2020/10"
  },
  {
    "title": "The Weeknd - False Alarm (Vevo Presents)",
    "url": "https://kworb.net/youtube../video/97NVHwPM8-4.html",
    "views": "4,239,830",
    "yesterday": "330",
    "publish": "2016/12"
  },
  {
    "title": "The Weeknd Backstage Warmups",
    "url": "https://kworb.net/youtube../video/jxhjY8e7CRY.html",
    "views": "4,173,878",
    "yesterday": "525",
    "publish": "2014/04"
  },
  {
    "title": "The Weeknd - Don't Break My Heart (Official LyricVideo)",
    "url": "https://kworb.net/youtube../video/OeqV6oyNHc0.html",
    "views": "4,166,403",
    "yesterday": "3,108",
    "publish": "2022/01"
  },
  {
    "title": "The Weeknd - Here We Go… Again (Audio) ft. Tyler, The Creator",
    "url": "https://kworb.net/youtube../video/_WMkhkbF6js.html",
    "views": "4,159,043",
    "yesterday": "1,059",
    "publish": "2022/01"
  },
  {
    "title": "The Weeknd - The Hills remix feat. Eminem ( A Virtual Reality Experience)",
    "url": "https://kworb.net/youtube../video/2fhjdtQDcOo.html",
    "views": "3,939,828",
    "yesterday": "261",
    "publish": "2015/10"
  },
  {
    "title": "The Weeknd - Don’t Break My Heart (Audio)",
    "url": "https://kworb.net/youtube../video/PHFWp5s-KNQ.html",
    "views": "3,857,533",
    "yesterday": "2,206",
    "publish": "2022/01"
  },
  {
    "title": "The Weeknd - I Feel It Coming (Audio) ft. Daft Punk",
    "url": "https://kworb.net/youtube../video/5v1TOFULOWA.html",
    "views": "3,789,204",
    "yesterday": "10,726",
    "publish": "2023/03"
  },
  {
    "title": "The Weeknd - Take My Breath (Extended Version) (Official Audio)",
    "url": "https://kworb.net/youtube../video/qYbm8HJlwMs.html",
    "views": "3,745,347",
    "yesterday": "1,514",
    "publish": "2021/08"
  },
  {
    "title": "The Weeknd - Can’t Feel My Face (Vevo Presents)",
    "url": "https://kworb.net/youtube../video/a_7t9y4hZGo.html",
    "views": "3,640,638",
    "yesterday": "206",
    "publish": "2015/08"
  },
  {
    "title": "The Weeknd - Echoes of Silence (Official Music Video)",
    "url": "https://kworb.net/youtube../video/bHFc5ZfEdBQ.html",
    "views": "3,605,283",
    "yesterday": "1,531",
    "publish": "2021/12"
  },
  {
    "title": "The Weeknd: Live at SoFi Stadium - Die For You",
    "url": "https://kworb.net/youtube../video/wX0anflee0U.html",
    "views": "3,545,162",
    "yesterday": "3,975",
    "publish": "2023/02"
  },
  {
    "title": "The Weeknd - Starry Eyes (Audio)",
    "url": "https://kworb.net/youtube../video/kDGyiXAMJAk.html",
    "views": "3,443,890",
    "yesterday": "4,901",
    "publish": "2022/01"
  },
  {
    "title": "The Weeknd ft. Tyler, The Creator - Here We Go… Again (Official Lyric Video)",
    "url": "https://kworb.net/youtube../video/rhVqSATlmQs.html",
    "views": "3,368,224",
    "yesterday": "1,653",
    "publish": "2022/01"
  },
  {
    "title": "The Weeknd - Until I Bleed Out (Audio)",
    "url": "https://kworb.net/youtube../video/iv1_FOdJ5s0.html",
    "views": "3,314,909",
    "yesterday": "1,194",
    "publish": "2020/03"
  },
  {
    "title": "He Was Never There, Docupoem",
    "url": "https://kworb.net/youtube../video/ZHBYGpAlNog.html",
    "views": "3,253,874",
    "yesterday": "368",
    "publish": "2018/04"
  },
  {
    "title": "The Weeknd - The Hills ft. Nicki Minaj (Live on SNL)",
    "url": "https://kworb.net/youtube../video/EusT7GqGZbg.html",
    "views": "3,197,254",
    "yesterday": "180",
    "publish": "2015/10"
  },
  {
    "title": "The Weeknd x The Dawn FM Experience - Out of Time",
    "url": "https://kworb.net/youtube../video/fgMV0ZJwBOw.html",
    "views": "3,142,183",
    "yesterday": "1,262",
    "publish": "2022/02"
  },
  {
    "title": "The Weeknd x The Dawn FM Experience - Is There Someone Else",
    "url": "https://kworb.net/youtube../video/TfEwkrTPyMk.html",
    "views": "3,108,374",
    "yesterday": "1,147",
    "publish": "2022/03"
  },
  {
    "title": "The Weeknd - The Hills (RL Grime Remix)",
    "url": "https://kworb.net/youtube../video/PrwB6qsL6fU.html",
    "views": "3,028,878",
    "yesterday": "269",
    "publish": "2015/11"
  },
  {
    "title": "The Weeknd - Live For feat. Drake (Official Video)",
    "url": "https://kworb.net/youtube../video/IqLlfuLrhxM.html",
    "views": "2,848,393",
    "yesterday": "107",
    "publish": "2013/09"
  },
  {
    "title": "The Weeknd & Lily-Rose Depp – Dollhouse (Official Audio)",
    "url": "https://kworb.net/youtube../video/rccD5TC5g_o.html",
    "views": "2,842,814",
    "yesterday": "13,815",
    "publish": "2023/07"
  },
  {
    "title": "The Weeknd - A Lonely Night (Audio)",
    "url": "https://kworb.net/youtube../video/iBnLoAE9kUE.html",
    "views": "2,810,708",
    "yesterday": "16,270",
    "publish": "2023/03"
  },
  {
    "title": "The Weeknd - Heaven Or Las Vegas",
    "url": "https://kworb.net/youtube../video/dXbJ8-38yHw.html",
    "views": "2,717,991",
    "yesterday": "394",
    "publish": "2011/08"
  },
  {
    "title": "The Weeknd - Heartless (Lyric Video)",
    "url": "https://kworb.net/youtube../video/KbWjNgPJRA0.html",
    "views": "2,712,880",
    "yesterday": "142",
    "publish": "2019/12"
  },
  {
    "title": "The Weeknd - Losers (Live at Apple Music Festival: London 2015)",
    "url": "https://kworb.net/youtube../video/jWsdlH3qizM.html",
    "views": "2,695,123",
    "yesterday": "186",
    "publish": "2015/10"
  },
  {
    "title": "The Weeknd - Gasoline (Official Lyric Video)",
    "url": "https://kworb.net/youtube../video/AWZF4Em0cwU.html",
    "views": "2,679,445",
    "yesterday": "1,002",
    "publish": "2022/01"
  },
  {
    "title": "The Weeknd - Starry Eyes (Official Lyric Video)",
    "url": "https://kworb.net/youtube../video/_GA3dj_HxO4.html",
    "views": "2,678,554",
    "yesterday": "1,777",
    "publish": "2022/01"
  },
  {
    "title": "The Weeknd - Sacrifice (Official Lyric Video)",
    "url": "https://kworb.net/youtube../video/jh0v2SAIW5o.html",
    "views": "2,598,728",
    "yesterday": "882",
    "publish": "2022/01"
  },
  {
    "title": "The Weeknd - Heartless (Remix) [feat. Lil Uzi Vert] (Official Audio)",
    "url": "https://kworb.net/youtube../video/vhr0zSJFS2c.html",
    "views": "2,572,321",
    "yesterday": "448",
    "publish": "2020/04"
  },
  {
    "title": "The Weeknd, KAYTRANADA - Out of Time (KAYTRANADA Remix / Audio)",
    "url": "https://kworb.net/youtube../video/zuUNNu3z5Uk.html",
    "views": "2,565,019",
    "yesterday": "324",
    "publish": "2022/04"
  },
  {
    "title": "The Weeknd - Phantom Regret by Jim (Audio)",
    "url": "https://kworb.net/youtube../video/vCOXTEzfoJ4.html",
    "views": "2,553,042",
    "yesterday": "1,071",
    "publish": "2022/01"
  },
  {
    "title": "The Weeknd - Six Feet Under (Audio)",
    "url": "https://kworb.net/youtube../video/Yu7kHJqKRW8.html",
    "views": "2,538,299",
    "yesterday": "10,723",
    "publish": "2023/03"
  },
  {
    "title": "The Weeknd - Can’t Feel My Face (Alternate Video)",
    "url": "https://kworb.net/youtube../video/ntMD9G9u1rI.html",
    "views": "2,530,214",
    "yesterday": "389",
    "publish": "2021/09"
  },
  {
    "title": "The Weeknd - Take Me Back (Official Audio)",
    "url": "https://kworb.net/youtube../video/cSPE7lNR73o.html",
    "views": "2,526,473",
    "yesterday": "4,759",
    "publish": "2023/06"
  },
  {
    "title": "The Weeknd - Love In The Sky",
    "url": "https://kworb.net/youtube../video/weweLG6Or-g.html",
    "views": "2,475,729",
    "yesterday": "278",
    "publish": "2013/07"
  },
  {
    "title": "The Weeknd x The Dawn FM Experience - Less Than Zero",
    "url": "https://kworb.net/youtube../video/gKVdq0FtQXc.html",
    "views": "2,470,640",
    "yesterday": "1,254",
    "publish": "2022/03"
  },
  {
    "title": "The Idol | Official Teaser | HBO",
    "url": "https://kworb.net/youtube../video/l5trYh8m1vs.html",
    "views": "2,444,478",
    "yesterday": "1,159",
    "publish": "2022/07"
  },
  {
    "title": "The Weeknd - Ordinary Life (Audio)",
    "url": "https://kworb.net/youtube../video/PlJV9IesfIk.html",
    "views": "2,405,138",
    "yesterday": "12,328",
    "publish": "2023/03"
  },
  {
    "title": "The Weeknd - A Lesser Man (Official Audio)",
    "url": "https://kworb.net/youtube../video/bBqrgxAr_sk.html",
    "views": "2,370,395",
    "yesterday": "4,371",
    "publish": "2023/06"
  },
  {
    "title": "Beauty Behind The Madness “The Leak” (Official)",
    "url": "https://kworb.net/youtube../video/zfgw9W7Tw5g.html",
    "views": "2,271,351",
    "yesterday": "",
    "publish": "2015/08"
  },
  {
    "title": "The Weeknd - A Tale By Quincy (Audio)",
    "url": "https://kworb.net/youtube../video/ioL_Ozo_6iI.html",
    "views": "2,228,787",
    "yesterday": "1,132",
    "publish": "2022/01"
  },
  {
    "title": "The Weeknd - High For This (Vevo Presents)",
    "url": "https://kworb.net/youtube../video/CRvAEic_KeU.html",
    "views": "2,156,964",
    "yesterday": "196",
    "publish": "2015/08"
  },
  {
    "title": "The Weeknd - After Hours (The Blaze Remix / Audio)",
    "url": "https://kworb.net/youtube../video/7mXlbEMfk_Y.html",
    "views": "2,097,584",
    "yesterday": "1,066",
    "publish": "2020/03"
  },
  {
    "title": "Suzanna Son & The Weeknd - Family (Official Audio)",
    "url": "https://kworb.net/youtube../video/1ztt-NkU7GE.html",
    "views": "2,074,668",
    "yesterday": "3,616",
    "publish": "2023/06"
  },
  {
    "title": "The Weeknd - Like A God (Official Audio)",
    "url": "https://kworb.net/youtube../video/Zf9dUVTa93s.html",
    "views": "1,986,825",
    "yesterday": "5,148",
    "publish": "2023/06"
  },
  {
    "title": "The Weeknd - House of Balloons / Glass Table Girls (Vevo Presents)",
    "url": "https://kworb.net/youtube../video/Nk6Zau-LKtg.html",
    "views": "1,925,589",
    "yesterday": "520",
    "publish": "2015/08"
  },
  {
    "title": "The Weeknd - Tell Your Friends (Vevo Presents)",
    "url": "https://kworb.net/youtube../video/3YbIleDN6lE.html",
    "views": "1,916,210",
    "yesterday": "186",
    "publish": "2015/08"
  },
  {
    "title": "The Weeknd - Blinding Lights (Live on The Late Show with Stephen Colbert / 2019)",
    "url": "https://kworb.net/youtube../video/kMQSbqZZEfA.html",
    "views": "1,901,086",
    "yesterday": "110",
    "publish": "2020/01"
  },
  {
    "title": "The Weeknd, Summer Walker - Best Friends (Remix)",
    "url": "https://kworb.net/youtube../video/wsRFSpjvZyg.html",
    "views": "1,887,309",
    "yesterday": "928",
    "publish": "2022/08"
  },
  {
    "title": "The Weeknd - All I Know (Audio) ft. Future",
    "url": "https://kworb.net/youtube../video/4iSEJB1KJ0w.html",
    "views": "1,878,779",
    "yesterday": "3,709",
    "publish": "2023/03"
  },
  {
    "title": "The Weeknd, Lil Baby, Suzanna Son – False Idols (Official Audio)",
    "url": "https://kworb.net/youtube../video/_JZW2ET4zQs.html",
    "views": "1,790,574",
    "yesterday": "4,106",
    "publish": "2023/06"
  },
  {
    "title": "The Weeknd x The Dawn FM Experience - Take My Breath",
    "url": "https://kworb.net/youtube../video/BnBhE9s2Rhk.html",
    "views": "1,734,032",
    "yesterday": "741",
    "publish": "2022/02"
  },
  {
    "title": "THE IDOL JUNE 4TH Official Teaser",
    "url": "https://kworb.net/youtube../video/PIvb1skN5BE.html",
    "views": "1,662,032",
    "yesterday": "1,783",
    "publish": "2023/04"
  },
  {
    "title": "The Weeknd - Secrets (Audio)",
    "url": "https://kworb.net/youtube../video/nh3Nc2XsdM0.html",
    "views": "1,653,805",
    "yesterday": "10,029",
    "publish": "2023/03"
  },
  {
    "title": "The Weeknd - Call Out My Name (Live at SoFi Stadium) (Official Audio)",
    "url": "https://kworb.net/youtube../video/xLeMvXEiNhw.html",
    "views": "1,613,823",
    "yesterday": "3,600",
    "publish": "2023/03"
  },
  {
    "title": "The Weeknd - Like A God (Music from the HBO Original Series The Idol)",
    "url": "https://kworb.net/youtube../video/p1D7pg-vtf0.html",
    "views": "1,608,254",
    "yesterday": "2,176",
    "publish": "2023/07"
  },
  {
    "title": "The Idol | Official Teaser 2 | HBO",
    "url": "https://kworb.net/youtube../video/QFNYgVAsY_o.html",
    "views": "1,604,036",
    "yesterday": "209",
    "publish": "2022/08"
  },
  {
    "title": "The Weeknd - Jealous Guy (Official Audio)",
    "url": "https://kworb.net/youtube../video/VN0pIgNZ61c.html",
    "views": "1,576,072",
    "yesterday": "3,403",
    "publish": "2023/06"
  },
  {
    "title": "The Dawn Is Coming (Teaser)",
    "url": "https://kworb.net/youtube../video/DQ7C0aE0I4M.html",
    "views": "1,550,263",
    "yesterday": "149",
    "publish": "2021/08"
  },
  {
    "title": "The Weeknd - Blinding Lights (Chromatics Remix / Audio) ft. Chromatics",
    "url": "https://kworb.net/youtube../video/1waU0C0gogE.html",
    "views": "1,519,849",
    "yesterday": "105",
    "publish": "2020/03"
  },
  {
    "title": "The Weeknd - False Alarm (Audio)",
    "url": "https://kworb.net/youtube../video/7uf8xkknCxQ.html",
    "views": "1,511,064",
    "yesterday": "6,757",
    "publish": "2023/03"
  },
  {
    "title": "The Weeknd - Every Angel Is Terrifying (Official Lyric Video)",
    "url": "https://kworb.net/youtube../video/kMXs99tPkcg.html",
    "views": "1,502,916",
    "yesterday": "722",
    "publish": "2022/01"
  },
  {
    "title": "Metro Boomin, The Weeknd, Diddy, & 21 Savage - Creepin (Remix) [Official Audio]",
    "url": "https://kworb.net/youtube../video/_qPtl2w75K4.html",
    "views": "1,481,669",
    "yesterday": "1,721",
    "publish": "2023/03"
  },
  {
    "title": "The Weeknd for Dolby Atmos",
    "url": "https://kworb.net/youtube../video/xDJmlyHs37c.html",
    "views": "1,432,400",
    "yesterday": "3,247",
    "publish": "2021/09"
  },
  {
    "title": "The Weeknd - Sidewalks (Audio) ft. Kendrick Lamar",
    "url": "https://kworb.net/youtube../video/sK-T-cmznY8.html",
    "views": "1,401,154",
    "yesterday": "5,453",
    "publish": "2023/03"
  },
  {
    "title": "The Weeknd - Gasoline (XO Vision)",
    "url": "https://kworb.net/youtube../video/PaTe6aJd4LA.html",
    "views": "1,349,270",
    "yesterday": "226",
    "publish": "2022/01"
  },
  {
    "title": "The Weeknd - Every Angel Is Terrifying (Audio)",
    "url": "https://kworb.net/youtube../video/_gaCXN99pC8.html",
    "views": "1,313,117",
    "yesterday": "336",
    "publish": "2022/01"
  },
  {
    "title": "The Weeknd - Jealous Guy (Music from the HBO Original Series The Idol)",
    "url": "https://kworb.net/youtube../video/tLyR03numQ8.html",
    "views": "1,236,747",
    "yesterday": "3,381",
    "publish": "2023/06"
  },
  {
    "title": "The Weeknd - Blinding Lights (Major Lazer Remix) [Official Audio]",
    "url": "https://kworb.net/youtube../video/9-YvMytXD9E.html",
    "views": "1,233,213",
    "yesterday": "322",
    "publish": "2020/04"
  },
  {
    "title": "The Weeknd - Heartless (Vapor Wave Remix / Audio) ft. Lil Uzi Vert",
    "url": "https://kworb.net/youtube../video/9F6SWhiFl8c.html",
    "views": "1,225,846",
    "yesterday": "490",
    "publish": "2020/03"
  },
  {
    "title": "The Weeknd, Metro Boomin & Mike Dean - Live @ Coachella",
    "url": "https://kworb.net/youtube../video/NfSw4ZI8yAg.html",
    "views": "1,135,607",
    "yesterday": "1,696",
    "publish": "2023/05"
  },
  {
    "title": "The Idol | Official Teaser 3 | HBO",
    "url": "https://kworb.net/youtube../video/fAaNq1txx1E.html",
    "views": "1,101,244",
    "yesterday": "155",
    "publish": "2022/10"
  },
  {
    "title": "The Weeknd - Heartless (Remix) [feat. Lil Uzi Vert] Intermission",
    "url": "https://kworb.net/youtube../video/UcaO-GpdwVY.html",
    "views": "1,093,991",
    "yesterday": "205",
    "publish": "2020/04"
  },
  {
    "title": "The Weeknd - True Colors (Audio)",
    "url": "https://kworb.net/youtube../video/VQ5XQYpx2mg.html",
    "views": "1,030,439",
    "yesterday": "4,352",
    "publish": "2023/03"
  },
  {
    "title": "The Weeknd - Sacrifice (XO Vision)",
    "url": "https://kworb.net/youtube../video/hKwqJunHsuw.html",
    "views": "1,029,324",
    "yesterday": "152",
    "publish": "2022/01"
  },
  {
    "title": "The Weeknd - The Making Of Take My Breath",
    "url": "https://kworb.net/youtube../video/0YKhWm0cP1c.html",
    "views": "1,020,150",
    "yesterday": "61",
    "publish": "2021/08"
  },
  {
    "title": "The Weeknd - Starry Eyes (Mike Dean Remix) (Official Audio)",
    "url": "https://kworb.net/youtubehttps://www.youtube.com/watch?v=qzdZgwdHGJw",
    "views": "996,724",
    "yesterday": "337",
    "publish": "2022/07"
  },
  {
    "title": "The Weeknd - Nothing Without You (Audio)",
    "url": "https://kworb.net/youtubehttps://www.youtube.com/watch?v=WFO7r3g-JBc",
    "views": "977,997",
    "yesterday": "4,335",
    "publish": "2023/03"
  },
  {
    "title": "The Weeknd & Mike Dean - The Lure (Main Theme) [Official Audio]",
    "url": "https://kworb.net/youtubehttps://www.youtube.com/watch?v=YhdZFxKtafY",
    "views": "920,953",
    "yesterday": "1,285",
    "publish": "2023/06"
  },
  {
    "title": "The Weeknd - Trailer (Official Live Performance)",
    "url": "https://kworb.net/youtubehttps://www.youtube.com/watch?v=WdBQ7q9z7rE",
    "views": "899,101",
    "yesterday": "55",
    "publish": "2020/11"
  },
  {
    "title": "The Weeknd - After Hours (Live at SoFi Stadium) (Official Audio)",
    "url": "https://kworb.net/youtubehttps://www.youtube.com/watch?v=5P89RDW71q4",
    "views": "885,672",
    "yesterday": "1,600",
    "publish": "2023/03"
  },
  {
    "title": "The Weeknd - Save Your Tears (OPN Remix / Audio)",
    "url": "https://kworb.net/youtubehttps://www.youtube.com/watch?v=O4KfX-JoJY4",
    "views": "865,719",
    "yesterday": "94",
    "publish": "2020/03"
  },
  {
    "title": "The Weeknd - Take My Breath (XO Lens)",
    "url": "https://kworb.net/youtubehttps://www.youtube.com/watch?v=YDymsaNxjuA",
    "views": "849,762",
    "yesterday": "75",
    "publish": "2021/08"
  },
  {
    "title": "The Weeknd - Take Me Back (Music from the HBO Original Series The Idol)",
    "url": "https://kworb.net/youtubehttps://www.youtube.com/watch?v=sQXI0o2FCHA",
    "views": "844,011",
    "yesterday": "2,593",
    "publish": "2023/06"
  },
  {
    "title": "The Weeknd - Rockin’ (Audio)",
    "url": "https://kworb.net/youtubehttps://www.youtube.com/watch?v=Nox2RGWOOdE",
    "views": "821,257",
    "yesterday": "3,148",
    "publish": "2023/03"
  },
  {
    "title": "The Weeknd - How Do I Make You Love Me (Sebastian Ingrosso & Salvatore Ganacci) (Official Audio)",
    "url": "https://kworb.net/youtubehttps://www.youtube.com/watch?v=lnKjqgcoc3c",
    "views": "809,967",
    "yesterday": "304",
    "publish": "2022/07"
  },
  {
    "title": "After Hours Til Dawn Tour - First Leg Recap",
    "url": "https://kworb.net/youtubehttps://www.youtube.com/watch?v=Is14IzzmfuM",
    "views": "784,723",
    "yesterday": "343",
    "publish": "2023/01"
  },
  {
    "title": "The Weeknd - Love To Lay (Audio)",
    "url": "https://kworb.net/youtubehttps://www.youtube.com/watch?v=dB4YSEHG3ac",
    "views": "718,511",
    "yesterday": "3,080",
    "publish": "2023/03"
  },
  {
    "title": "The Weeknd - Attention (Audio)",
    "url": "https://kworb.net/youtubehttps://www.youtube.com/watch?v=3tHuJAZpYNw",
    "views": "669,001",
    "yesterday": "2,277",
    "publish": "2023/03"
  },
  {
    "title": "The Weeknd - A Lesser Man (Music from the HBO Original Series The Idol)",
    "url": "https://kworb.net/youtubehttps://www.youtube.com/watch?v=-WW2Ni24AzU",
    "views": "655,977",
    "yesterday": "2,241",
    "publish": "2023/06"
  },
  {
    "title": "The Weeknd - Dawn FM (OPN Remix) (Official Audio)",
    "url": "https://kworb.net/youtubehttps://www.youtube.com/watch?v=5yl44zWtGSk",
    "views": "638,784",
    "yesterday": "187",
    "publish": "2022/07"
  },
  {
    "title": "The Weeknd & Ariana Grande - Die For You (Remix Acapella) [Official Audio]",
    "url": "https://kworb.net/youtubehttps://www.youtube.com/watch?v=xVGRi-NvHZM",
    "views": "617,880",
    "yesterday": "310",
    "publish": "2023/03"
  },
  {
    "title": "The Weeknd - Can’t Feel My Face (Live On SNL)",
    "url": "https://kworb.net/youtubehttps://www.youtube.com/watch?v=EPestjXw2nw",
    "views": "606,749",
    "yesterday": "27",
    "publish": "2015/10"
  },
  {
    "title": "Mike Dean - Devil's Paradise (Music from the HBO Original Series The Idol)",
    "url": "https://kworb.net/youtubehttps://www.youtube.com/watch?v=v0G1-PbyLrI",
    "views": "535,334",
    "yesterday": "1,769",
    "publish": "2023/06"
  },
  {
    "title": "The Weeknd x Club Paradise",
    "url": "https://kworb.net/youtubehttps://www.youtube.com/watch?v=Q277kO4OREQ",
    "views": "522,938",
    "yesterday": "39",
    "publish": "2012/05"
  },
  {
    "title": "Drake and The Weeknd \"Would You Like A Tour\" OVO & XO",
    "url": "https://kworb.net/youtubehttps://www.youtube.com/watch?v=saEEMD997ns",
    "views": "480,704",
    "yesterday": "21",
    "publish": "2014/03"
  },
  {
    "title": "The Weeknd - Take My Breath (Instrumental) (Official Audio)",
    "url": "https://kworb.net/youtubehttps://www.youtube.com/watch?v=BOtuzmEei7w",
    "views": "464,985",
    "yesterday": "239",
    "publish": "2021/08"
  },
  {
    "title": "Troye Sivan – My Sweet Lord (Official Audio)",
    "url": "https://kworb.net/youtubehttps://www.youtube.com/watch?v=XsFDcdHGXSc",
    "views": "462,391",
    "yesterday": "836",
    "publish": "2023/07"
  },
  {
    "title": "The Weeknd, Suzanna Son - Family (Music from the HBO Original Series The Idol)",
    "url": "https://kworb.net/youtubehttps://www.youtube.com/watch?v=kzDsr4I6_Z8",
    "views": "458,111",
    "yesterday": "1,327",
    "publish": "2023/06"
  },
  {
    "title": "The Weeknd - The Hills (Live at SoFi Stadium) (Official Audio)",
    "url": "https://kworb.net/youtubehttps://www.youtube.com/watch?v=lSF_SCLi9Pk",
    "views": "442,511",
    "yesterday": "765",
    "publish": "2023/03"
  },
  {
    "title": "The Weeknd - Reminder (Audio) ft. A$AP Rocky, Young Thug",
    "url": "https://kworb.net/youtubehttps://www.youtube.com/watch?v=lmpwdV99Yh4",
    "views": "393,666",
    "yesterday": "394",
    "publish": "2023/03"
  },
  {
    "title": "Mike Dean - Devil's Paradise (Official Audio)",
    "url": "https://kworb.net/youtubehttps://www.youtube.com/watch?v=ifLpA9izsVI",
    "views": "391,989",
    "yesterday": "463",
    "publish": "2023/06"
  },
  {
    "title": "The Weeknd - Live At Sofi Stadium Trailer (HBO Concert Special)",
    "url": "https://kworb.net/youtubehttps://www.youtube.com/watch?v=NUApaq14x64",
    "views": "388,832",
    "yesterday": "305",
    "publish": "2023/02"
  },
  {
    "title": "The Weeknd - Starboy (After Hours (Live at SoFi Stadium) (Official Audio)",
    "url": "https://kworb.net/youtubehttps://www.youtube.com/watch?v=AYF3AmntvvE",
    "views": "388,764",
    "yesterday": "858",
    "publish": "2023/03"
  },
  {
    "title": "The Weeknd - Often (Live at SoFi Stadium) (Official Audio)",
    "url": "https://kworb.net/youtubehttps://www.youtube.com/watch?v=4kmItvIAceQ",
    "views": "371,165",
    "yesterday": "738",
    "publish": "2023/03"
  },
  {
    "title": "The Weeknd - Sacrifice (Live at SoFi Stadium) (Official Audio)",
    "url": "https://kworb.net/youtubehttps://www.youtube.com/watch?v=8HqneWmke6Y",
    "views": "370,923",
    "yesterday": "827",
    "publish": "2023/03"
  },
  {
    "title": "The Weeknd - Blinding Lights (Live at SoFi Stadium) (Official Audio)",
    "url": "https://kworb.net/youtubehttps://www.youtube.com/watch?v=YKh1Diq0ohM",
    "views": "369,530",
    "yesterday": "734",
    "publish": "2023/03"
  },
  {
    "title": "The Weeknd - Out of Time (Live at SoFi Stadium) (Official Audio)",
    "url": "https://kworb.net/youtubehttps://www.youtube.com/watch?v=rWwIKXfg3xw",
    "views": "349,346",
    "yesterday": "648",
    "publish": "2023/03"
  },
  {
    "title": "The Weeknd x Paris",
    "url": "https://kworb.net/youtubehttps://www.youtube.com/watch?v=VwvL1Yvp72M",
    "views": "348,516",
    "yesterday": "14",
    "publish": "2014/04"
  },
  {
    "title": "The Weeknd - Party Monster (Live at SoFi Stadium) (Official Audio)",
    "url": "https://kworb.net/youtubehttps://www.youtube.com/watch?v=0wqA16EhFsY",
    "views": "339,966",
    "yesterday": "684",
    "publish": "2023/03"
  },
  {
    "title": "The Weeknd - Is There Someone Else? (After Hours (Live At SoFi) /Pseudo Video)",
    "url": "https://kworb.net/youtubehttps://www.youtube.com/watch?v=EwAvtt9Rc3A",
    "views": "338,538",
    "yesterday": "629",
    "publish": "2023/03"
  },
  {
    "title": "Beauty Behind The Madness",
    "url": "https://kworb.net/youtubehttps://www.youtube.com/watch?v=3XIYasaR1SQ",
    "views": "332,947",
    "yesterday": "73",
    "publish": "2015/08"
  },
  {
    "title": "The Weeknd, Future - Double Fantasy (Music from the HBO Original Series The Idol)",
    "url": "https://kworb.net/youtubehttps://www.youtube.com/watch?v=MzLlA9npN2Q",
    "views": "326,120",
    "yesterday": "912",
    "publish": "2023/06"
  },
  {
    "title": "The Weeknd, Mike Dean - The Lure (Main Theme) (Music from the HBO Original Series The Idol)",
    "url": "https://kworb.net/youtubehttps://www.youtube.com/watch?v=tCAOKs-66H8",
    "views": "293,125",
    "yesterday": "511",
    "publish": "2023/06"
  },
  {
    "title": "Suzanna Son - Crocodile Tears (Official Audio)",
    "url": "https://kworb.net/youtubehttps://www.youtube.com/watch?v=_rwtRKFhwtM",
    "views": "287,723",
    "yesterday": "515",
    "publish": "2023/07"
  },
  {
    "title": "The Weeknd - I Was Never There (Live at SoFi Stadium) (Official Audio)",
    "url": "https://kworb.net/youtubehttps://www.youtube.com/watch?v=PZPhrc9s82Y",
    "views": "275,773",
    "yesterday": "470",
    "publish": "2023/03"
  },
  {
    "title": "The Weeknd - Scared To Live (Live On Saturday Night Live / 2020 / Audio)",
    "url": "https://kworb.net/youtubehttps://www.youtube.com/watch?v=MCg8YfDQYLY",
    "views": "270,334",
    "yesterday": "42",
    "publish": "2020/03"
  },
  {
    "title": "The Weeknd, Ty Dolla $ign - Or Nah (After Hours (Live at SoFi Stadium) (Official Audio)",
    "url": "https://kworb.net/youtubehttps://www.youtube.com/watch?v=rlAXQ4rYpFA",
    "views": "267,293",
    "yesterday": "460",
    "publish": "2023/03"
  },
  {
    "title": "The Weeknd - Alone Again (Live at SoFi Stadium) (Official Audio)",
    "url": "https://kworb.net/youtubehttps://www.youtube.com/watch?v=OaNd22q_Ej4",
    "views": "267,256",
    "yesterday": "398",
    "publish": "2023/03"
  },
  {
    "title": "The Weeknd - Intro (After Hours (Live at SoFi Stadium) (Official Audio)",
    "url": "https://kworb.net/youtubehttps://www.youtube.com/watch?v=PEy-6nzfuis",
    "views": "245,519",
    "yesterday": "337",
    "publish": "2023/03"
  },
  {
    "title": "Moses Sumney - Get It B4",
    "url": "https://kworb.net/youtubehttps://www.youtube.com/watch?v=w__JeJM212U",
    "views": "241,859",
    "yesterday": "320",
    "publish": "2023/06"
  },
  {
    "title": "The Weeknd - Less Than Zero (Live at SoFi Stadium) (Official Audio)",
    "url": "https://kworb.net/youtubehttps://www.youtube.com/watch?v=-zv5IVoamr4",
    "views": "239,560",
    "yesterday": "341",
    "publish": "2023/03"
  },
  {
    "title": "The Weeknd - Take My Breath (After Hours (Live at SoFi Stadium) (Official Audio)",
    "url": "https://kworb.net/youtubehttps://www.youtube.com/watch?v=6-7JZMJc1Ck",
    "views": "239,404",
    "yesterday": "513",
    "publish": "2023/03"
  },
  {
    "title": "The Weeknd - Echoes of Silence (Behind The Scene Documentary)",
    "url": "https://kworb.net/youtubehttps://www.youtube.com/watch?v=mlnB13VUEUw",
    "views": "239,194",
    "yesterday": "34",
    "publish": "2021/12"
  },
  {
    "title": "The Weeknd - Heartless (Live at SoFi Stadium) (Official Audio)",
    "url": "https://kworb.net/youtubehttps://www.youtube.com/watch?v=tnvNDkdOZHA",
    "views": "227,939",
    "yesterday": "371",
    "publish": "2023/03"
  },
  {
    "title": "The Weeknd - Gasoline (After Hours (Live At SoFi) /Pseudo Video)",
    "url": "https://kworb.net/youtubehttps://www.youtube.com/watch?v=4ujIFFMY4V4",
    "views": "224,928",
    "yesterday": "415",
    "publish": "2023/03"
  },
  {
    "title": "The Weeknd - Hurricane (After Hours (Live at SoFi Stadium) (Official Audio)",
    "url": "https://kworb.net/youtubehttps://www.youtube.com/watch?v=YqS3zSetGNE",
    "views": "221,367",
    "yesterday": "427",
    "publish": "2023/03"
  },
  {
    "title": "The Weeknd - Faith (After Hours (Live at SoFi Stadium) (Official Audio)",
    "url": "https://kworb.net/youtubehttps://www.youtube.com/watch?v=io4Vw5oT18k",
    "views": "219,280",
    "yesterday": "335",
    "publish": "2023/03"
  },
  {
    "title": "The Weeknd - How Do I Make You Love Me? (Live at SoFi Stadium) (Official Audio)",
    "url": "https://kworb.net/youtubehttps://www.youtube.com/watch?v=RxIrj_CBi1M",
    "views": "209,152",
    "yesterday": "406",
    "publish": "2023/03"
  },
  {
    "title": "The Weeknd - Die For You (Live at SoFi Stadium) (Official Audio)",
    "url": "https://kworb.net/youtubehttps://www.youtube.com/watch?v=HRa30JXI7Qg",
    "views": "208,807",
    "yesterday": "372",
    "publish": "2023/03"
  },
  {
    "title": "Kiss Land - Melrose Ave. Los Angeles",
    "url": "https://kworb.net/youtubehttps://www.youtube.com/watch?v=YVjvGIqa1X8",
    "views": "195,017",
    "yesterday": "16",
    "publish": "2013/09"
  },
  {
    "title": "The Weeknd - I Feel It Coming (Live at SoFi Stadium) (Official Audio)",
    "url": "https://kworb.net/youtubehttps://www.youtube.com/watch?v=WbzSLuEfUAI",
    "views": "194,942",
    "yesterday": "351",
    "publish": "2023/03"
  },
  {
    "title": "The Weeknd - Save Your Tears (Live at SoFi Stadium) (Official Audio)",
    "url": "https://kworb.net/youtubehttps://www.youtube.com/watch?v=KTR6PIWOp_Q",
    "views": "194,574",
    "yesterday": "320",
    "publish": "2023/03"
  },
  {
    "title": "The Weeknd - Wicked Games (Live at SoFi Stadium) (Official Audio)",
    "url": "https://kworb.net/youtubehttps://www.youtube.com/watch?v=DUvLKU03uNA",
    "views": "174,410",
    "yesterday": "269",
    "publish": "2023/03"
  },
  {
    "title": "The Weeknd x The Dawn FM Experience - How Do I Make You Love Me",
    "url": "https://kworb.net/youtubehttps://www.youtube.com/watch?v=eOpVjbBb-nM",
    "views": "169,680",
    "yesterday": "",
    "publish": "2022/03"
  },
  {
    "title": "The Weeknd - Can't Feel My Face (Live at SoFi Stadium) (Official Audio)",
    "url": "https://kworb.net/youtubehttps://www.youtube.com/watch?v=G-vdOGua2Ng",
    "views": "160,462",
    "yesterday": "290",
    "publish": "2023/03"
  },
  {
    "title": "The Weeknd - Low Life (Live at SoFi Stadium) (Official Audio)",
    "url": "https://kworb.net/youtubehttps://www.youtube.com/watch?v=cBMNJk3sGWo",
    "views": "154,405",
    "yesterday": "316",
    "publish": "2023/03"
  },
  {
    "title": "The Weeknd - The Morning (Live at SoFi Stadium) (Official Audio)",
    "url": "https://kworb.net/youtubehttps://www.youtube.com/watch?v=V5tVUL5ykHQ",
    "views": "147,146",
    "yesterday": "231",
    "publish": "2023/03"
  },
  {
    "title": "The Weeknd - Crew (After Hours (Live at SoFi Stadium) (Official Audio)",
    "url": "https://kworb.net/youtubehttps://www.youtube.com/watch?v=kNC9E3m_u14",
    "views": "144,568",
    "yesterday": "300",
    "publish": "2023/03"
  },
  {
    "title": "Kiss Land - Wicker Park, Chicago",
    "url": "https://kworb.net/youtubehttps://www.youtube.com/watch?v=euQdiW6_gCo",
    "views": "139,284",
    "yesterday": "15",
    "publish": "2013/09"
  },
  {
    "title": "The Weeknd - Starboy (Audio) ft. Daft Punk",
    "url": "https://kworb.net/youtubehttps://www.youtube.com/watch?v=q-cKwdoa3X8",
    "views": "128,661",
    "yesterday": "363",
    "publish": "2023/03"
  },
  {
    "title": "The Weeknd x The Dawn FM Experience - Dawn FM/Gasoline",
    "url": "https://kworb.net/youtubehttps://www.youtube.com/watch?v=dXg4L7AWMq0",
    "views": "112,478",
    "yesterday": "",
    "publish": "2022/03"
  },
  {
    "title": "The Weeknd - Kiss Land (Live at SoFi Stadium) (Official Audio)",
    "url": "https://kworb.net/youtubehttps://www.youtube.com/watch?v=4STR7nslVu0",
    "views": "105,956",
    "yesterday": "182",
    "publish": "2023/03"
  }
]